django_loadjson-0.1.0.dist-info/DESCRIPTION.rst
django_loadjson-0.1.0.dist-info/METADATA
django_loadjson-0.1.0.dist-info/RECORD
django_loadjson-0.1.0.dist-info/WHEEL
django_loadjson-0.1.0.dist-info/metadata.json
django_loadjson-0.1.0.dist-info/top_level.txt
loadjson/__init__.py
loadjson/adaptors.py
loadjson/compat.py
loadjson/finders.py
loadjson/loaders.py
loadjson/management/__init__.py
loadjson/management/commands/__init__.py
loadjson/management/commands/loadjson.py
loadjson/tests/__init__.py
loadjson/tests/finders.py
loadjson/tests/models.py
loadjson/tests/settings.py
loadjson/tests/test.py
loadjson/tests/test_loaders.py
