Metadata-Version: 2.0
Name: django-loadjson
Version: 0.1.0
Summary: Loadjson management command for Django
Home-page: https://github.com/onebit0fme/django-loadjson
Author: Terry Yanchynskyy
Author-email: tarasics@gmail.com
License: MIT
Keywords: django management json
Platform: UNKNOWN
Classifier: Development Status :: 3 - Alpha
Classifier: Environment :: Console
Classifier: License :: OSI Approved :: MIT License
Classifier: Operating System :: OS Independent
Classifier: Programming Language :: Python :: 2.7
Classifier: Programming Language :: Python :: 3.2
Classifier: Programming Language :: Python :: 3.3
Classifier: Programming Language :: Python :: 3.4
Classifier: Programming Language :: Python :: 3.5
Classifier: Topic :: Software Development :: Libraries :: Python Modules
Classifier: Framework :: Django
Classifier: Framework :: Django :: 1.7
Classifier: Framework :: Django :: 1.8
Classifier: Framework :: Django :: 1.9
Classifier: Intended Audience :: Developers
Requires-Dist: django (>=1.7)
Requires-Dist: python-dateutil
Requires-Dist: six
